binance/__init__.py
binance/__version__.py
binance/api.py
binance/error.py
binance/lib/__init__.py
binance/lib/authentication.py
binance/lib/enums.py
binance/lib/utils.py
binance/spot/__init__.py
binance/spot/_auto_invest.py
binance/spot/_blvt.py
binance/spot/_bswap.py
binance/spot/_c2c.py
binance/spot/_convert.py
binance/spot/_crypto_loan.py
binance/spot/_data_stream.py
binance/spot/_fiat.py
binance/spot/_futures.py
binance/spot/_gift_card.py
binance/spot/_margin.py
binance/spot/_market.py
binance/spot/_mining.py
binance/spot/_nft.py
binance/spot/_pay.py
binance/spot/_portfolio_margin.py
binance/spot/_rebate.py
binance/spot/_simple_earn.py
binance/spot/_staking.py
binance/spot/_sub_account.py
binance/spot/_trade.py
binance/spot/_wallet.py
binance/websocket/__init__.py
binance/websocket/binance_socket_manager.py
binance/websocket/websocket_client.py
binance/websocket/spot/__init__.py
binance/websocket/spot/websocket_stream.py
binance/websocket/spot/websocket_api/__init__.py
binance/websocket/spot/websocket_api/_account.py
binance/websocket/spot/websocket_api/_market.py
binance/websocket/spot/websocket_api/_trade.py
binance/websocket/spot/websocket_api/_user_data.py
examples/__init__.py
binance_connector_zxw-3.4.0.dist-info/LICENSE.md
binance_connector_zxw-3.4.0.dist-info/METADATA
binance_connector_zxw-3.4.0.dist-info/WHEEL
binance_connector_zxw-3.4.0.dist-info/top_level.txt
binance_connector_zxw-3.4.0.dist-info/RECORD
