Metadata-Version: 2.1
Name: binance-connector-zxw
Version: 3.4.0
Summary: 修复了原版的binance-connector-python的websocket连接丢失无法捕获错误的BUG，使其可以正常运行
Home-page: https://github.com/sunshineinwater/binance-connector-python-zxw
License: MIT
Keywords: Binance,Public API
Classifier: Intended Audience :: Developers
Classifier: Intended Audience :: Financial and Insurance Industry
Classifier: License :: OSI Approved :: MIT License
Classifier: Programming Language :: Python :: 3.8
Classifier: Programming Language :: Python :: 3.9
Classifier: Programming Language :: Python :: 3.10
Classifier: Programming Language :: Python :: 3.11
Requires-Python: >=3.8
License-File: LICENSE.md
Requires-Dist: requests (>=2.31.0)
Requires-Dist: websocket-client (>=1.6.3)
Requires-Dist: pycryptodome (>=3.15.0)
